openai_batch_helper/__init__.py
openai_batch_helper/__main__.py
openai_batch_helper/cli.py
openai_batch_helper/core.py
openai_batch_helper/exceptions.py
openai_batch_helper/io.py
openai_batch_helper/py.typed
openai_batch_helper/typing.py
openai_batch_helper/version.py
openai_batch_helper-0.1.1.dist-info/licenses/LICENSE
openai_batch_helper-0.1.1.dist-info/METADATA
openai_batch_helper-0.1.1.dist-info/WHEEL
openai_batch_helper-0.1.1.dist-info/entry_points.txt
openai_batch_helper-0.1.1.dist-info/top_level.txt
openai_batch_helper-0.1.1.dist-info/RECORD
