Metadata-Version: 2.4
Name: openai-batch-helper
Version: 0.1.1
Summary: Tiny, production-friendly helper for the OpenAI Batch API
Author: hesenp
License: MIT License
Project-URL: Homepage, https://github.com/hesenp/openai_batch_helper
Project-URL: Repository, https://github.com/hesenp/openai_batch_helper
Project-URL: Documentation, https://openai-batch-helper.readthedocs.io
Project-URL: Changelog, https://github.com/hesenp/openai_batch_helper/blob/main/CHANGELOG.md
Project-URL: Bug Tracker, https://github.com/hesenp/openai_batch_helper/issues
Keywords: openai,batch,cli,api
Classifier: Development Status :: 3 - Alpha
Classifier: Intended Audience :: Developers
Classifier: License :: OSI Approved :: MIT License
Classifier: Programming Language :: Python :: 3 :: Only
Classifier: Programming Language :: Python :: 3.9
Classifier: Programming Language :: Python :: 3.10
Classifier: Programming Language :: Python :: 3.11
Classifier: Programming Language :: Python :: 3.12
Classifier: Topic :: Software Development :: Libraries
Classifier: Topic :: Utilities
Requires-Python: >=3.9
License-File: LICENSE
Requires-Dist: openai>=1.0.0
Provides-Extra: dev
Requires-Dist: pytest; extra == "dev"
Requires-Dist: pytest-cov; extra == "dev"
Requires-Dist: mypy; extra == "dev"
Requires-Dist: ruff; extra == "dev"
Requires-Dist: types-requests; extra == "dev"
Requires-Dist: bandit; extra == "dev"
Requires-Dist: safety; extra == "dev"
Requires-Dist: build; extra == "dev"
Requires-Dist: twine; extra == "dev"
Requires-Dist: sphinx>=6; extra == "dev"
Requires-Dist: furo>=2024.1.29; extra == "dev"
Provides-Extra: docs
Requires-Dist: sphinx>=6; extra == "docs"
Requires-Dist: furo>=2024.1.29; extra == "docs"
Dynamic: license-file
